keelson/Envelope_pb2.py
keelson/Envelope_pb2.pyi
keelson/__init__.py
keelson/codec.py
keelson/subjects.yaml
keelson/utils.py
keelson/interfaces/Configurable_pb2.py
keelson/interfaces/Configurable_pb2.pyi
keelson/interfaces/ErrorResponse_pb2.py
keelson/interfaces/ErrorResponse_pb2.pyi
keelson/interfaces/NetworkPingPong_pb2.py
keelson/interfaces/NetworkPingPong_pb2.pyi
keelson/interfaces/Subscriber_pb2.py
keelson/interfaces/Subscriber_pb2.pyi
keelson/interfaces/WHEPProxy_pb2.py
keelson/interfaces/WHEPProxy_pb2.pyi
keelson/payloads/Alarm_pb2.py
keelson/payloads/Alarm_pb2.pyi
keelson/payloads/Audio_pb2.py
keelson/payloads/Audio_pb2.pyi
keelson/payloads/Decomposed3DVector_pb2.py
keelson/payloads/Decomposed3DVector_pb2.pyi
keelson/payloads/FlagCode_pb2.py
keelson/payloads/FlagCode_pb2.pyi
keelson/payloads/Geojson_pb2.py
keelson/payloads/Geojson_pb2.pyi
keelson/payloads/LocationFixQuality_pb2.py
keelson/payloads/LocationFixQuality_pb2.pyi
keelson/payloads/NetworkStatus_pb2.py
keelson/payloads/NetworkStatus_pb2.pyi
keelson/payloads/Primitives_pb2.py
keelson/payloads/Primitives_pb2.pyi
keelson/payloads/ROCStatus_pb2.py
keelson/payloads/ROCStatus_pb2.pyi
keelson/payloads/RadarReading_pb2.py
keelson/payloads/RadarReading_pb2.pyi
keelson/payloads/SensorStatus_pb2.py
keelson/payloads/SensorStatus_pb2.pyi
keelson/payloads/SimulationStatus_pb2.py
keelson/payloads/SimulationStatus_pb2.pyi
keelson/payloads/TargetType_pb2.py
keelson/payloads/TargetType_pb2.pyi
keelson/payloads/VesselNavStatus_pb2.py
keelson/payloads/VesselNavStatus_pb2.pyi
keelson/payloads/VesselType_pb2.py
keelson/payloads/VesselType_pb2.pyi
keelson/payloads/protobuf_file_descriptor_set.bin
keelson/payloads/foxglove/ArrowPrimitive_pb2.py
keelson/payloads/foxglove/ArrowPrimitive_pb2.pyi
keelson/payloads/foxglove/CameraCalibration_pb2.py
keelson/payloads/foxglove/CameraCalibration_pb2.pyi
keelson/payloads/foxglove/CircleAnnotation_pb2.py
keelson/payloads/foxglove/CircleAnnotation_pb2.pyi
keelson-0.4.4.dist-info/METADATA
keelson-0.4.4.dist-info/WHEEL
keelson-0.4.4.dist-info/entry_points.txt
keelson-0.4.4.dist-info/top_level.txt
keelson-0.4.4.dist-info/RECORD
