Metadata-Version: 2.4
Name: keelson
Version: 0.4.4
Summary: A python Software Development Kit for keelson
Home-page: https://github.com/rise-maritime/keelson/sdks/python
Author: Fredrik Olsson
Author-email: fredrik.x.olsson@ri.se
Maintainer: Fredrik Olsson
Maintainer-email: fredrik.x.olsson@ri.se
License: Apache License 2.0
Requires-Python: >=3.7
Requires-Dist: eclipse-zenoh>=1.2.1
Requires-Dist: protobuf>=5.29.1
Requires-Dist: pyyaml
Requires-Dist: parse
Dynamic: author
Dynamic: author-email
Dynamic: description
Dynamic: description-content-type
Dynamic: home-page
Dynamic: license
Dynamic: maintainer
Dynamic: maintainer-email
Dynamic: requires-dist
Dynamic: requires-python
Dynamic: summary
